odoo/addons/mrp_bom_structure_xlsx/README.rst
odoo/addons/mrp_bom_structure_xlsx/__init__.py
odoo/addons/mrp_bom_structure_xlsx/__manifest__.py
odoo/addons/mrp_bom_structure_xlsx/i18n/de.po
odoo/addons/mrp_bom_structure_xlsx/report/__init__.py
odoo/addons/mrp_bom_structure_xlsx/report/bom_structure_xlsx.py
odoo/addons/mrp_bom_structure_xlsx/report/bom_structure_xlsx.xml
odoo/addons/mrp_bom_structure_xlsx/static/description/icon.png
odoo/addons/mrp_bom_structure_xlsx/static/description/index.html
odoo11_addon_mrp_bom_structure_xlsx-11.0.1.0.0.dist-info/DESCRIPTION.rst
odoo11_addon_mrp_bom_structure_xlsx-11.0.1.0.0.dist-info/METADATA
odoo11_addon_mrp_bom_structure_xlsx-11.0.1.0.0.dist-info/RECORD
odoo11_addon_mrp_bom_structure_xlsx-11.0.1.0.0.dist-info/WHEEL
odoo11_addon_mrp_bom_structure_xlsx-11.0.1.0.0.dist-info/metadata.json
odoo11_addon_mrp_bom_structure_xlsx-11.0.1.0.0.dist-info/top_level.txt
